[
  {
    "title": "RBC Capital Reiterates \u201cOutperform\u201d Rating and $810 PT On Meta Platforms (META) Amid Explosion In AI-Enabled Entrepreneurialism",
    "summary": "",
    "link": "https://finance.yahoo.com/markets/stocks/articles/rbc-capital-reiterates-outperform-rating-161113693.html",
    "source": "Yahoo Finance",
    "tickers": [
      "META"
    ],
    "impact": 2,
    "bull": true,
    "bear": false,
    "time": "2026-06-04T16:32:04.788416",
    "recent": true
  },
  {
    "title": "Nvidia, Meta and SLB rank among top companies in adopting AI, new study says",
    "summary": "The AI-Driven Enterprise Institute released new research that breaks down the degree to which S&amp;P 500 companies are adopting AI compared with their peers.",
    "link": "https://www.cnbc.com/2026/06/01/nvidia-meta-walmart-among-top-companies-adopting-ai.html",
    "source": "CNBC",
    "tickers": [
      "META",
      "SLB"
    ],
    "impact": 0,
    "bull": false,
    "bear": false,
    "time": "2026-06-04T16:32:03.907754",
    "recent": false
  }
]