{
  "VIX": {
    "price": 15.78,
    "change": -2.29,
    "time": "2026-07-03T15:37:35.845959"
  },
  "DXY": {
    "price": 100.85,
    "change": -0.01,
    "time": "2026-07-03T15:37:35.873968"
  },
  "TLT": {
    "price": 85.51,
    "change": -0.01,
    "time": "2026-07-03T15:37:35.961663"
  },
  "TNX": {
    "price": 4.48,
    "change": 0.0,
    "time": "2026-07-03T15:37:36.024029"
  },
  "SPY": {
    "price": 744.78,
    "change": -0.13,
    "time": "2026-07-03T15:37:36.121152"
  },
  "NVDA": {
    "price": 194.83,
    "change": 0.0,
    "time": "2026-07-03T15:37:36.195003"
  },
  "QCOM": {
    "price": 176.25,
    "change": 0.0,
    "time": "2026-07-03T15:37:36.294451"
  },
  "AVGO": {
    "price": 360.45,
    "change": 0.0,
    "time": "2026-07-03T15:37:36.510325"
  },
  "ARM": {
    "price": 315.28,
    "change": 0.0,
    "time": "2026-07-03T15:37:36.596337"
  },
  "SMH": {
    "price": 592.29,
    "change": 0.0,
    "time": "2026-07-03T15:37:36.672131"
  },
  "SOXX": {
    "price": 566.32,
    "change": 0.0,
    "time": "2026-07-03T15:37:36.756250"
  },
  "LRCX": {
    "price": 351.41,
    "change": 0.0,
    "time": "2026-07-03T15:37:36.835223"
  },
  "KLAC": {
    "price": 235.55,
    "change": 0.0,
    "time": "2026-07-03T15:37:36.907151"
  },
  "ASML": {
    "price": 1769.32,
    "change": 0.0,
    "time": "2026-07-03T15:37:36.983242"
  },
  "MRVL": {
    "price": 245.29,
    "change": 0.0,
    "time": "2026-07-03T15:37:37.062867"
  },
  "ARKX": {
    "price": 33.87,
    "change": 0.0,
    "time": "2026-07-03T15:37:37.130840"
  },
  "CLOU": {
    "price": 23.22,
    "change": 0.0,
    "time": "2026-07-03T15:37:37.203243"
  },
  "CIBR": {
    "price": 90.67,
    "change": 0.0,
    "time": "2026-07-03T15:37:37.282456"
  },
  "INTC": {
    "price": 120.35,
    "change": 0.0,
    "time": "2026-07-03T15:37:37.359419"
  },
  "MU": {
    "price": 975.56,
    "change": 0.0,
    "time": "2026-07-03T15:37:37.453955"
  },
  "SNDK": {
    "price": 1745.0,
    "change": 0.0,
    "time": "2026-07-03T15:37:37.531351"
  },
  "AMAT": {
    "price": 603.04,
    "change": 0.0,
    "time": "2026-07-03T15:37:37.613695"
  },
  "XLK": {
    "price": 180.59,
    "change": 0.0,
    "time": "2026-07-03T15:37:37.693700"
  },
  "BOTZ": {
    "price": 37.39,
    "change": 0.0,
    "time": "2026-07-03T15:37:37.760709"
  },
  "AMD": {
    "price": 517.82,
    "change": 0.0,
    "time": "2026-07-03T15:37:37.836974"
  },
  "TSM": {
    "price": 434.16,
    "change": 0.0,
    "time": "2026-07-03T15:37:37.908445"
  },
  "ARKQ": {
    "price": 127.94,
    "change": 0.0,
    "time": "2026-07-03T15:37:37.976264"
  },
  "ARKG": {
    "price": 42.91,
    "change": 0.0,
    "time": "2026-07-03T15:37:38.047290"
  },
  "HACK": {
    "price": 106.97,
    "change": 0.0,
    "time": "2026-07-03T15:37:38.116200"
  },
  "ROBT": {
    "price": 56.25,
    "change": 0.0,
    "time": "2026-07-03T15:37:38.192592"
  },
  "ARKF": {
    "price": 40.97,
    "change": 0.0,
    "time": "2026-07-03T15:37:38.261033"
  },
  "WCLD": {
    "price": 33.52,
    "change": 0.0,
    "time": "2026-07-03T15:37:38.331119"
  },
  "SMCI": {
    "price": 27.22,
    "change": 0.0,
    "time": "2026-07-03T15:37:38.406996"
  },
  "ARKK": {
    "price": 81.25,
    "change": 0.0,
    "time": "2026-07-03T15:37:38.474359"
  },
  "IGV": {
    "price": 93.57,
    "change": 0.0,
    "time": "2026-07-03T15:37:38.550592"
  }
}