{
  "VIX": {
    "price": 15.57,
    "change": -1.7,
    "time": "2026-07-10T15:59:40.235213"
  },
  "DXY": {
    "price": 100.81,
    "change": -0.1,
    "time": "2026-07-10T15:59:40.321516"
  },
  "TLT": {
    "price": 84.61,
    "change": 0.14,
    "time": "2026-07-10T15:59:40.424297"
  },
  "TNX": {
    "price": 4.54,
    "change": 0.13,
    "time": "2026-07-10T15:59:40.483818"
  },
  "SPY": {
    "price": 752.76,
    "change": 0.14,
    "time": "2026-07-10T15:59:40.608726"
  },
  "SOXX": {
    "price": 578.52,
    "change": 0.0,
    "time": "2026-07-10T15:59:40.671633"
  },
  "ARKX": {
    "price": 32.02,
    "change": 0.0,
    "time": "2026-07-10T15:59:40.733059"
  },
  "LRCX": {
    "price": 349.25,
    "change": 0.0,
    "time": "2026-07-10T15:59:40.801665"
  },
  "SMH": {
    "price": 608.2,
    "change": 0.0,
    "time": "2026-07-10T15:59:40.831620"
  },
  "CLOU": {
    "price": 23.8,
    "change": 0.0,
    "time": "2026-07-10T15:59:40.896192"
  },
  "INTC": {
    "price": 109.13,
    "change": 0.0,
    "time": "2026-07-10T15:59:40.964096"
  },
  "QCOM": {
    "price": 188.41,
    "change": 0.0,
    "time": "2026-07-10T15:59:41.031491"
  },
  "AVGO": {
    "price": 400.69,
    "change": 0.0,
    "time": "2026-07-10T15:59:41.145798"
  },
  "TSM": {
    "price": 433.0,
    "change": 0.0,
    "time": "2026-07-10T15:59:41.219436"
  },
  "SNDK": {
    "price": 1873.91,
    "change": 0.0,
    "time": "2026-07-10T15:59:41.303571"
  },
  "KLAC": {
    "price": 228.03,
    "change": 0.0,
    "time": "2026-07-10T15:59:41.362911"
  },
  "ASML": {
    "price": 1793.03,
    "change": 0.0,
    "time": "2026-07-10T15:59:41.456843"
  },
  "ARM": {
    "price": 323.61,
    "change": 0.0,
    "time": "2026-07-10T15:59:41.520576"
  },
  "MRVL": {
    "price": 236.4,
    "change": 0.0,
    "time": "2026-07-10T15:59:41.603387"
  },
  "ARKQ": {
    "price": 123.61,
    "change": 0.0,
    "time": "2026-07-10T15:59:41.668613"
  },
  "BOTZ": {
    "price": 36.9,
    "change": 0.0,
    "time": "2026-07-10T15:59:41.728902"
  },
  "AMAT": {
    "price": 599.47,
    "change": 0.0,
    "time": "2026-07-10T15:59:41.799185"
  },
  "SMCI": {
    "price": 28.61,
    "change": 0.0,
    "time": "2026-07-10T15:59:41.855678"
  },
  "CIBR": {
    "price": 92.03,
    "change": 0.0,
    "time": "2026-07-10T15:59:41.949040"
  },
  "MU": {
    "price": 970.09,
    "change": 0.0,
    "time": "2026-07-10T15:59:42.014826"
  },
  "XLK": {
    "price": 184.97,
    "change": 0.0,
    "time": "2026-07-10T15:59:42.079608"
  },
  "HACK": {
    "price": 109.22,
    "change": 0.0,
    "time": "2026-07-10T15:59:42.173516"
  },
  "ROBT": {
    "price": 56.02,
    "change": 0.0,
    "time": "2026-07-10T15:59:42.256210"
  },
  "NVDA": {
    "price": 209.03,
    "change": 0.0,
    "time": "2026-07-10T15:59:42.321110"
  },
  "ARKK": {
    "price": 80.39,
    "change": 0.0,
    "time": "2026-07-10T15:59:42.386262"
  },
  "ARKG": {
    "price": 41.02,
    "change": 0.0,
    "time": "2026-07-10T15:59:42.444902"
  },
  "ARKF": {
    "price": 41.82,
    "change": 0.0,
    "time": "2026-07-10T15:59:42.509346"
  },
  "AMD": {
    "price": 550.66,
    "change": 0.0,
    "time": "2026-07-10T15:59:42.583532"
  },
  "IGV": {
    "price": 92.63,
    "change": 0.0,
    "time": "2026-07-10T15:59:42.654467"
  },
  "WCLD": {
    "price": 33.98,
    "change": 0.0,
    "time": "2026-07-10T15:59:42.722723"
  }
}