{
  "VIX": {
    "price": 16.9,
    "change": 4.77,
    "time": "2026-07-08T20:44:14.077636"
  },
  "DXY": {
    "price": 101.04,
    "change": 0.02,
    "time": "2026-07-08T20:44:14.271681"
  },
  "TLT": {
    "price": 84.36,
    "change": -0.22,
    "time": "2026-07-08T20:44:14.465065"
  },
  "TNX": {
    "price": 4.57,
    "change": 0.88,
    "time": "2026-07-08T20:44:14.641464"
  },
  "SPY": {
    "price": 745.4,
    "change": -0.31,
    "time": "2026-07-08T20:44:14.893339"
  },
  "QCOM": {
    "price": 186.56,
    "change": 0.0,
    "time": "2026-07-08T20:44:15.048686"
  },
  "MU": {
    "price": 948.8,
    "change": 0.0,
    "time": "2026-07-08T20:44:15.305744"
  },
  "KLAC": {
    "price": 221.18,
    "change": 0.0,
    "time": "2026-07-08T20:44:15.483814"
  },
  "ASML": {
    "price": 1768.65,
    "change": 0.0,
    "time": "2026-07-08T20:44:15.659848"
  },
  "GOOGL": {
    "price": 361.92,
    "change": 0.0,
    "time": "2026-07-08T20:44:15.886935"
  },
  "SMH": {
    "price": 593.0,
    "change": 0.0,
    "time": "2026-07-08T20:44:16.059370"
  },
  "SOXX": {
    "price": 562.03,
    "change": 0.0,
    "time": "2026-07-08T20:44:16.253936"
  },
  "AMD": {
    "price": 517.4,
    "change": 0.0,
    "time": "2026-07-08T20:44:16.412055"
  },
  "INTC": {
    "price": 110.24,
    "change": 0.0,
    "time": "2026-07-08T20:44:16.615971"
  },
  "TSM": {
    "price": 436.98,
    "change": 0.0,
    "time": "2026-07-08T20:44:16.772278"
  },
  "LRCX": {
    "price": 333.15,
    "change": 0.0,
    "time": "2026-07-08T20:44:16.931307"
  },
  "ARM": {
    "price": 300.24,
    "change": 0.0,
    "time": "2026-07-08T20:44:17.094637"
  },
  "MRVL": {
    "price": 231.71,
    "change": 0.0,
    "time": "2026-07-08T20:44:17.299061"
  },
  "SMCI": {
    "price": 28.17,
    "change": 0.0,
    "time": "2026-07-08T20:44:17.482837"
  },
  "PLTR": {
    "price": 132.22,
    "change": 0.0,
    "time": "2026-07-08T20:44:17.664063"
  },
  "AAPL": {
    "price": 313.39,
    "change": 0.0,
    "time": "2026-07-08T20:44:17.861537"
  },
  "MSFT": {
    "price": 383.34,
    "change": 0.0,
    "time": "2026-07-08T20:44:18.040603"
  },
  "TSLA": {
    "price": 394.06,
    "change": 0.0,
    "time": "2026-07-08T20:44:18.222805"
  },
  "CRM": {
    "price": 166.58,
    "change": 0.0,
    "time": "2026-07-08T20:44:18.402831"
  },
  "NOW": {
    "price": 107.78,
    "change": 0.0,
    "time": "2026-07-08T20:44:18.565879"
  },
  "ARKQ": {
    "price": 123.81,
    "change": 0.0,
    "time": "2026-07-08T20:44:18.903312"
  },
  "AMAT": {
    "price": 570.5,
    "change": 0.0,
    "time": "2026-07-08T20:44:19.087689"
  },
  "XLK": {
    "price": 181.4,
    "change": 0.0,
    "time": "2026-07-08T20:44:19.265443"
  },
  "NVDA": {
    "price": 204.12,
    "change": 0.0,
    "time": "2026-07-08T20:44:19.444439"
  },
  "SNDK": {
    "price": 1727.18,
    "change": 0.0,
    "time": "2026-07-08T20:44:19.622147"
  },
  "AMZN": {
    "price": 243.62,
    "change": 0.0,
    "time": "2026-07-08T20:44:19.801751"
  },
  "NFLX": {
    "price": 75.59,
    "change": 0.0,
    "time": "2026-07-08T20:44:20.008860"
  },
  "META": {
    "price": 603.12,
    "change": 0.0,
    "time": "2026-07-08T20:44:20.184320"
  },
  "ARKK": {
    "price": 80.16,
    "change": 0.0,
    "time": "2026-07-08T20:44:20.341772"
  },
  "AVGO": {
    "price": 388.69,
    "change": 0.0,
    "time": "2026-07-08T20:44:20.499397"
  }
}